LICENSE
README.md
setup.py
propelauth_fastapi/__init__.py
propelauth_fastapi.egg-info/PKG-INFO
propelauth_fastapi.egg-info/SOURCES.txt
propelauth_fastapi.egg-info/dependency_links.txt
propelauth_fastapi.egg-info/requires.txt
propelauth_fastapi.egg-info/top_level.txt