Metadata-Version: 2.1
Name: propelauth-fastapi
Version: 4.2.8
Summary: A FastAPI library for managing authentication, backed by PropelAuth
Home-page: https://github.com/propelauth/propelauth-fastapi
Author: PropelAuth
Author-email: support@propelauth.com
License: MIT
Platform: UNKNOWN
License-File: LICENSE
